draft/__init__.py
draft/command.py
draft/constants.py
draft/drafttool.py
draft/exceptions.py
draft/utils.py
draft/version.py
ddraft_cmd_tool-0.1.1.dist-info/LICENSE
ddraft_cmd_tool-0.1.1.dist-info/METADATA
ddraft_cmd_tool-0.1.1.dist-info/WHEEL
ddraft_cmd_tool-0.1.1.dist-info/entry_points.txt
ddraft_cmd_tool-0.1.1.dist-info/top_level.txt
ddraft_cmd_tool-0.1.1.dist-info/RECORD
