Metadata-Version: 2.1
Name: ddraft_cmd_tool
Version: 0.1.1
Summary: Command line tools to organize and pack DungeonDraft custom assets
Author: Jacob Lee
Author-email: jacobianlee@gmail.com
Classifier: Programming Language :: Python :: 3
Classifier: Operating System :: OS Independent
License-File: LICENSE
Requires-Dist: pillow >=10.0.0
